[
    {"alaska": ["northwest_territory", "alberta", "kamchatka"]},
    {"northwest_territoy": ["alaska", "alberta", "ontario", "greenland"]},
    {"greenland": ["northwest_territory", "ontario", "quebec", "iceland"]},
    {"alberta": ["alaska", "northwest_territory", "ontario", "western_united_states"]},
    {"ontario": ["alberta", "northwest_territory", "greenland", "quebec", "western_united_states", "eastern_united_states"]},
    {"central_america": ["eastern_united_states", "western_united_states", "venezuela"]},

    {"venezuela": ["central_america", "peru", "brazil"]},
    {"peru": ["brazil", "venezuela", "argentina"]},
    {"argentina": ["brazil", "peru"]},
    {"brazil": ["venezuela", "peru", "argentina", "north_africa"]},

    {"iceland": ["greenland", "scandinavia", "great_britain"]},
    {"great_britain": ["iceland", "scandinavia", "western_europe"]},
    {"scandinavia": ["iceland", "great_britain", "ukraine", "northern_europe"]},
    {"northern_europe": ["great_britain", "western_europe", "southern_europe", "ukraine", "scandinavia"]},
    {"western_europe": ["great_britain", "northern_europe", "southern_europe", "north_africa"]},
    {"southern_europe": ["western_europe", "northern_europe", "ukraine", "middle_east", "egypt", "north_africa"]},
    {"ukraine": ["scandinavia", "northern_europe", "southern_europe", "middle_east", "ural", "afghanistan"]},

    {"north_africa": ["western_europe", "southern_europe", "egypt", "east_africa", "congo", "brazil"]},
    {"egypt": ["north_africa", "southern_europe", "middle_east", "east_africa"]},
    {"congo": ["north_africa", "south_africa", "east_africa"]},
    {"south_africa": ["congo", "east_africa", "madagascar"]},
    {"madagascar": ["south_africa", "east_africa"]},
    {"east_africa": ["north_africa", "egypt", "congo", "south_africa", "madagascar", "middle_east"]},
    
    {"ural": ["ukraine", "siberia", "afghanistan", "china"]},
    {"siberia": ["ural", "china", "yakursk", "irkutsk", "mongolia"]},
    {"yakursk": ["siberia", "irkutsk", "kamchatka"]},
    {"irkutsk": ["siberia", "yakursk", "kamchatka", "mongolia"]},
    {"kamchatka": ["yakursk", "irkutsk", "japan", "alaska", "mongolia"]},
    {"japan": ["kamchatka", "mongolia"]},
    {"mongolia": ["irkutsk", "siberia", "japan", "kamchatka", "china"]},
    {"afghanistan": ["ukraine", "ural", "china", "india", "middle_east"]},
    {"middle_east": ["ukraine", "east_africa", "southern_europe", "india", "afghanistan"]},
    {"india": ["middle_east", "afghanistan", "china", "siam"]},
    {"china": ["india", "siberia", "mongolia", "siam", "ural", "afghanistan"]},
    {"siam": ["china", "india", "indonesia"]},

    {"indonesia": ["new_guinea", "western_australia", "siam"]},
    {"new_guinea": ["indonesia", "western_australia", "eastern_australia"]},
    {"western_australia": ["indonesia", "new_guinea", "eastern_australia"]},
    {"eastern_australia": ["new_guinea", "western_australia"]}
]